bestvectors/__init__.py
bestvectors-1.0.1.dist-info/LICENSE.md
bestvectors-1.0.1.dist-info/METADATA
bestvectors-1.0.1.dist-info/WHEEL
bestvectors-1.0.1.dist-info/top_level.txt
bestvectors-1.0.1.dist-info/RECORD
