Metadata-Version: 2.1
Name: bestvectors
Version: 1.0.1
Summary: Vectors on a hexagonal grid. 
Author-email: Aaron Alphabet <aaron.alphabet@posteo.org>
Classifier: License :: OSI Approved :: MIT License
Classifier: Programming Language :: Python
Classifier: Programming Language :: Python :: 3
Requires-Python: >=3.11
License-File: LICENSE.md
